no_you_talk_to_the_hand.py
no_you_talk_to_the_hand-1.0.5.dist-info/LICENSE
no_you_talk_to_the_hand-1.0.5.dist-info/METADATA
no_you_talk_to_the_hand-1.0.5.dist-info/WHEEL
no_you_talk_to_the_hand-1.0.5.dist-info/entry_points.txt
no_you_talk_to_the_hand-1.0.5.dist-info/top_level.txt
no_you_talk_to_the_hand-1.0.5.dist-info/RECORD
