Metadata-Version: 2.1
Name: no-you-talk-to-the-hand
Version: 1.0.5
Summary: nyttth: Boss your corporate network effortlessly. Automatic and organized tunneling with sshuttle + supervisord + yaml
Home-page: https://github.com/flashashen/no-YOU-talk-to-the-hand
Author: flashashen
Author-email: flashashen@gmail.com
License: MIT
Keywords: ssh vpn tunnel forward daemon
Platform: osx
Platform: linux
Classifier: License :: OSI Approved :: MIT License
Classifier: Programming Language :: Python :: 2.7
Classifier: Topic :: System :: Networking
Classifier: Topic :: System :: Networking :: Firewalls
Classifier: Environment :: Console
Classifier: Operating System :: MacOS
Classifier: Operating System :: POSIX :: Linux
Classifier: Development Status :: 5 - Production/Stable
Requires-Dist: Click
Requires-Dist: supervisor
Requires-Dist: pyyaml (>=4.2b1)
Requires-Dist: jinja2
Requires-Dist: six
Requires-Dist: requests (>=2.20.0)
Requires-Dist: futures
Requires-Dist: sshuttle (==0.78.1)
